polars_ethan/__init__.py
polars_ethan/transforms.py
polars_ethan-0.3.0.dist-info/METADATA
polars_ethan-0.3.0.dist-info/WHEEL
polars_ethan-0.3.0.dist-info/top_level.txt
polars_ethan-0.3.0.dist-info/RECORD
